[
    {
        "label": "receiver",
        "importPath": "django.dispatch",
        "description": "django.dispatch",
        "isExtraImport": true,
        "detail": "django.dispatch",
        "documentation": {}
    },
    {
        "label": "pre_save",
        "importPath": "django.db.models.signals",
        "description": "django.db.models.signals",
        "isExtraImport": true,
        "detail": "django.db.models.signals",
        "documentation": {}
    },
    {
        "label": "post_save",
        "importPath": "django.db.models.signals",
        "description": "django.db.models.signals",
        "isExtraImport": true,
        "detail": "django.db.models.signals",
        "documentation": {}
    },
    {
        "label": "settings",
        "importPath": "django.conf",
        "description": "django.conf",
        "isExtraImport": true,
        "detail": "django.conf",
        "documentation": {}
    },
    {
        "label": "settings",
        "importPath": "django.conf",
        "description": "django.conf",
        "isExtraImport": true,
        "detail": "django.conf",
        "documentation": {}
    },
    {
        "label": "Agents",
        "importPath": "agents.models",
        "description": "agents.models",
        "isExtraImport": true,
        "detail": "agents.models",
        "documentation": {}
    },
    {
        "label": "admin",
        "importPath": "django.contrib",
        "description": "django.contrib",
        "isExtraImport": true,
        "detail": "django.contrib",
        "documentation": {}
    },
    {
        "label": "admin",
        "importPath": "django.contrib",
        "description": "django.contrib",
        "isExtraImport": true,
        "detail": "django.contrib",
        "documentation": {}
    },
    {
        "label": "admin",
        "importPath": "django.contrib",
        "description": "django.contrib",
        "isExtraImport": true,
        "detail": "django.contrib",
        "documentation": {}
    },
    {
        "label": "admin",
        "importPath": "django.contrib",
        "description": "django.contrib",
        "isExtraImport": true,
        "detail": "django.contrib",
        "documentation": {}
    },
    {
        "label": "admin",
        "importPath": "django.contrib",
        "description": "django.contrib",
        "isExtraImport": true,
        "detail": "django.contrib",
        "documentation": {}
    },
    {
        "label": "AppConfig",
        "importPath": "django.apps",
        "description": "django.apps",
        "isExtraImport": true,
        "detail": "django.apps",
        "documentation": {}
    },
    {
        "label": "AppConfig",
        "importPath": "django.apps",
        "description": "django.apps",
        "isExtraImport": true,
        "detail": "django.apps",
        "documentation": {}
    },
    {
        "label": "AppConfig",
        "importPath": "django.apps",
        "description": "django.apps",
        "isExtraImport": true,
        "detail": "django.apps",
        "documentation": {}
    },
    {
        "label": "AppConfig",
        "importPath": "django.apps",
        "description": "django.apps",
        "isExtraImport": true,
        "detail": "django.apps",
        "documentation": {}
    },
    {
        "label": "models",
        "importPath": "django.db",
        "description": "django.db",
        "isExtraImport": true,
        "detail": "django.db",
        "documentation": {}
    },
    {
        "label": "migrations",
        "importPath": "django.db",
        "description": "django.db",
        "isExtraImport": true,
        "detail": "django.db",
        "documentation": {}
    },
    {
        "label": "models",
        "importPath": "django.db",
        "description": "django.db",
        "isExtraImport": true,
        "detail": "django.db",
        "documentation": {}
    },
    {
        "label": "models",
        "importPath": "django.db",
        "description": "django.db",
        "isExtraImport": true,
        "detail": "django.db",
        "documentation": {}
    },
    {
        "label": "models",
        "importPath": "django.db",
        "description": "django.db",
        "isExtraImport": true,
        "detail": "django.db",
        "documentation": {}
    },
    {
        "label": "models",
        "importPath": "django.db",
        "description": "django.db",
        "isExtraImport": true,
        "detail": "django.db",
        "documentation": {}
    },
    {
        "label": "TestCase",
        "importPath": "django.test",
        "description": "django.test",
        "isExtraImport": true,
        "detail": "django.test",
        "documentation": {}
    },
    {
        "label": "TestCase",
        "importPath": "django.test",
        "description": "django.test",
        "isExtraImport": true,
        "detail": "django.test",
        "documentation": {}
    },
    {
        "label": "TestCase",
        "importPath": "django.test",
        "description": "django.test",
        "isExtraImport": true,
        "detail": "django.test",
        "documentation": {}
    },
    {
        "label": "TestCase",
        "importPath": "django.test",
        "description": "django.test",
        "isExtraImport": true,
        "detail": "django.test",
        "documentation": {}
    },
    {
        "label": "render",
        "importPath": "django.shortcuts",
        "description": "django.shortcuts",
        "isExtraImport": true,
        "detail": "django.shortcuts",
        "documentation": {}
    },
    {
        "label": "render",
        "importPath": "django.shortcuts",
        "description": "django.shortcuts",
        "isExtraImport": true,
        "detail": "django.shortcuts",
        "documentation": {}
    },
    {
        "label": "render",
        "importPath": "django.shortcuts",
        "description": "django.shortcuts",
        "isExtraImport": true,
        "detail": "django.shortcuts",
        "documentation": {}
    },
    {
        "label": "render",
        "importPath": "django.shortcuts",
        "description": "django.shortcuts",
        "isExtraImport": true,
        "detail": "django.shortcuts",
        "documentation": {}
    },
    {
        "label": "django.contrib.auth.models",
        "kind": 6,
        "isExtraImport": true,
        "importPath": "django.contrib.auth.models",
        "description": "django.contrib.auth.models",
        "detail": "django.contrib.auth.models",
        "documentation": {}
    },
    {
        "label": "AbstractUser",
        "importPath": "django.contrib.auth.models",
        "description": "django.contrib.auth.models",
        "isExtraImport": true,
        "detail": "django.contrib.auth.models",
        "documentation": {}
    },
    {
        "label": "django.contrib.auth.validators",
        "kind": 6,
        "isExtraImport": true,
        "importPath": "django.contrib.auth.validators",
        "description": "django.contrib.auth.validators",
        "detail": "django.contrib.auth.validators",
        "documentation": {}
    },
    {
        "label": "django.utils.timezone",
        "kind": 6,
        "isExtraImport": true,
        "importPath": "django.utils.timezone",
        "description": "django.utils.timezone",
        "detail": "django.utils.timezone",
        "documentation": {}
    },
    {
        "label": "serializers",
        "importPath": "rest_framework",
        "description": "rest_framework",
        "isExtraImport": true,
        "detail": "rest_framework",
        "documentation": {}
    },
    {
        "label": "status",
        "importPath": "rest_framework",
        "description": "rest_framework",
        "isExtraImport": true,
        "detail": "rest_framework",
        "documentation": {}
    },
    {
        "label": "UserCreateSerializer",
        "importPath": "djoser.serializers",
        "description": "djoser.serializers",
        "isExtraImport": true,
        "detail": "djoser.serializers",
        "documentation": {}
    },
    {
        "label": "UserSerializer",
        "importPath": "djoser.serializers",
        "description": "djoser.serializers",
        "isExtraImport": true,
        "detail": "djoser.serializers",
        "documentation": {}
    },
    {
        "label": "TokenCreateSerializer",
        "importPath": "djoser.serializers",
        "description": "djoser.serializers",
        "isExtraImport": true,
        "detail": "djoser.serializers",
        "documentation": {}
    },
    {
        "label": "CurrentPasswordSerializer",
        "importPath": "djoser.serializers",
        "description": "djoser.serializers",
        "isExtraImport": true,
        "detail": "djoser.serializers",
        "documentation": {}
    },
    {
        "label": "UserDeleteSerializer",
        "importPath": "djoser.serializers",
        "description": "djoser.serializers",
        "isExtraImport": true,
        "detail": "djoser.serializers",
        "documentation": {}
    },
    {
        "label": "authenticate",
        "importPath": "django.contrib.auth",
        "description": "django.contrib.auth",
        "isExtraImport": true,
        "detail": "django.contrib.auth",
        "documentation": {}
    },
    {
        "label": "login",
        "importPath": "django.contrib.auth",
        "description": "django.contrib.auth",
        "isExtraImport": true,
        "detail": "django.contrib.auth",
        "documentation": {}
    },
    {
        "label": "reverse",
        "importPath": "django.urls",
        "description": "django.urls",
        "isExtraImport": true,
        "detail": "django.urls",
        "documentation": {}
    },
    {
        "label": "include",
        "importPath": "django.urls",
        "description": "django.urls",
        "isExtraImport": true,
        "detail": "django.urls",
        "documentation": {}
    },
    {
        "label": "path",
        "importPath": "django.urls",
        "description": "django.urls",
        "isExtraImport": true,
        "detail": "django.urls",
        "documentation": {}
    },
    {
        "label": "include",
        "importPath": "django.urls",
        "description": "django.urls",
        "isExtraImport": true,
        "detail": "django.urls",
        "documentation": {}
    },
    {
        "label": "path",
        "importPath": "django.urls",
        "description": "django.urls",
        "isExtraImport": true,
        "detail": "django.urls",
        "documentation": {}
    },
    {
        "label": "os",
        "kind": 6,
        "isExtraImport": true,
        "importPath": "os",
        "description": "os",
        "detail": "os",
        "documentation": {}
    },
    {
        "label": "ProtocolTypeRouter",
        "importPath": "channels.routing",
        "description": "channels.routing",
        "isExtraImport": true,
        "detail": "channels.routing",
        "documentation": {}
    },
    {
        "label": "AllowedHostsOriginValidator",
        "importPath": "channels.security.websocket",
        "description": "channels.security.websocket",
        "isExtraImport": true,
        "detail": "channels.security.websocket",
        "documentation": {}
    },
    {
        "label": "SessionMiddlewareStack",
        "importPath": "channels.sessions",
        "description": "channels.sessions",
        "isExtraImport": true,
        "detail": "channels.sessions",
        "documentation": {}
    },
    {
        "label": "get_asgi_application",
        "importPath": "django.core.asgi",
        "description": "django.core.asgi",
        "isExtraImport": true,
        "detail": "django.core.asgi",
        "documentation": {}
    },
    {
        "label": "timedelta",
        "importPath": "datetime",
        "description": "datetime",
        "isExtraImport": true,
        "detail": "datetime",
        "documentation": {}
    },
    {
        "label": "Path",
        "importPath": "pathlib",
        "description": "pathlib",
        "isExtraImport": true,
        "detail": "pathlib",
        "documentation": {}
    },
    {
        "label": "load_dotenv",
        "importPath": "dotenv",
        "description": "dotenv",
        "isExtraImport": true,
        "detail": "dotenv",
        "documentation": {}
    },
    {
        "label": "get_wsgi_application",
        "importPath": "django.core.wsgi",
        "description": "django.core.wsgi",
        "isExtraImport": true,
        "detail": "django.core.wsgi",
        "documentation": {}
    },
    {
        "label": "HttpResponse",
        "importPath": "django.http",
        "description": "django.http",
        "isExtraImport": true,
        "detail": "django.http",
        "documentation": {}
    },
    {
        "label": "sys",
        "kind": 6,
        "isExtraImport": true,
        "importPath": "sys",
        "description": "sys",
        "detail": "sys",
        "documentation": {}
    },
    {
        "label": "create_agent_account",
        "kind": 2,
        "importPath": "agents.signals.handlers",
        "description": "agents.signals.handlers",
        "peekOfCode": "def create_agent_account(sender,**kwargs):\n    if kwargs['created']:\n        agent = Agents.objects.create(user=settings.AUTH_USER_MODEL)",
        "detail": "agents.signals.handlers",
        "documentation": {}
    },
    {
        "label": "@receiver(post_save,sender",
        "kind": 5,
        "importPath": "agents.signals.handlers",
        "description": "agents.signals.handlers",
        "peekOfCode": "@receiver(post_save,sender = settings.AUTH_USER_MODEL)\ndef create_agent_account(sender,**kwargs):\n    if kwargs['created']:\n        agent = Agents.objects.create(user=settings.AUTH_USER_MODEL)",
        "detail": "agents.signals.handlers",
        "documentation": {}
    },
    {
        "label": "AgentsConfig",
        "kind": 6,
        "importPath": "agents.apps",
        "description": "agents.apps",
        "peekOfCode": "class AgentsConfig(AppConfig):\n    default_auto_field = 'django.db.models.BigAutoField'\n    name = 'agents'\n    def ready(self) -> None:\n        import agents.signals.handlers",
        "detail": "agents.apps",
        "documentation": {}
    },
    {
        "label": "Agents",
        "kind": 6,
        "importPath": "agents.models",
        "description": "agents.models",
        "peekOfCode": "class Agents(models.Model):\n    user = models.OneToOneField(settings.AUTH_USER_MODEL,on_delete=models.CASCADE)\n    sector = models.CharField(max_length=255,default='customer_support')\n    ratings = models.DecimalField(decimal_places=2,max_digits=3,default=5.00)",
        "detail": "agents.models",
        "documentation": {}
    },
    {
        "label": "Migration",
        "kind": 6,
        "importPath": "core.migrations.0001_initial",
        "description": "core.migrations.0001_initial",
        "peekOfCode": "class Migration(migrations.Migration):\n    initial = True\n    dependencies = [\n        ('auth', '0012_alter_user_first_name_max_length'),\n    ]\n    operations = [\n        migrations.CreateModel(\n            name='User',\n            fields=[\n                ('id', models.BigAutoField(auto_created=True, primary_key=True, serialize=False, verbose_name='ID')),",
        "detail": "core.migrations.0001_initial",
        "documentation": {}
    },
    {
        "label": "CoreConfig",
        "kind": 6,
        "importPath": "core.apps",
        "description": "core.apps",
        "peekOfCode": "class CoreConfig(AppConfig):\n    default_auto_field = 'django.db.models.BigAutoField'\n    name = 'core'",
        "detail": "core.apps",
        "documentation": {}
    },
    {
        "label": "User",
        "kind": 6,
        "importPath": "core.models",
        "description": "core.models",
        "peekOfCode": "class User(AbstractUser):\n    email = models.EmailField(unique=True)",
        "detail": "core.models",
        "documentation": {}
    },
    {
        "label": "UserCreateSerializer",
        "kind": 6,
        "importPath": "core.serializers",
        "description": "core.serializers",
        "peekOfCode": "class UserCreateSerializer(BaseUserCreateSerializer):\n    class Meta(BaseUserCreateSerializer.Meta):\n        fields = ['email','username','password','first_name','last_name']\nclass UserSerializer(BaseUserSerializer):\n    class Meta(BaseUserSerializer.Meta):\n        fields = ['email','username','first_name','last_name']\n# class TokenCreateSerializer(BaseTokenCreateSerializer):\n#     pass\n# class CurrentPasswordSerializer(BaseCurrentPasswordSerializer):\n#     pass",
        "detail": "core.serializers",
        "documentation": {}
    },
    {
        "label": "UserSerializer",
        "kind": 6,
        "importPath": "core.serializers",
        "description": "core.serializers",
        "peekOfCode": "class UserSerializer(BaseUserSerializer):\n    class Meta(BaseUserSerializer.Meta):\n        fields = ['email','username','first_name','last_name']\n# class TokenCreateSerializer(BaseTokenCreateSerializer):\n#     pass\n# class CurrentPasswordSerializer(BaseCurrentPasswordSerializer):\n#     pass",
        "detail": "core.serializers",
        "documentation": {}
    },
    {
        "label": "django_asgi_app",
        "kind": 5,
        "importPath": "djangochannelsapp.asgi",
        "description": "djangochannelsapp.asgi",
        "peekOfCode": "django_asgi_app = get_asgi_application()\napplication = ProtocolTypeRouter({\n    \"http\": django_asgi_app,\n    # Just HTTP for now. (We can add other protocols later.)\n})",
        "detail": "djangochannelsapp.asgi",
        "documentation": {}
    },
    {
        "label": "application",
        "kind": 5,
        "importPath": "djangochannelsapp.asgi",
        "description": "djangochannelsapp.asgi",
        "peekOfCode": "application = ProtocolTypeRouter({\n    \"http\": django_asgi_app,\n    # Just HTTP for now. (We can add other protocols later.)\n})",
        "detail": "djangochannelsapp.asgi",
        "documentation": {}
    },
    {
        "label": "BASE_DIR",
        "kind": 5,
        "importPath": "djangochannelsapp.settings",
        "description": "djangochannelsapp.settings",
        "peekOfCode": "BASE_DIR = Path(__file__).resolve().parent.parent\n# Quick-start development settings - unsuitable for production\n# See https://docs.djangoproject.com/en/4.2/howto/deployment/checklist/\n# SECURITY WARNING: keep the secret key used in production secret!\nSECRET_KEY = 'django-insecure-cz9wb(svs7nzs3w(%b(l!7hc&ux)#84!g-rim5uthh^e^m1v#v'\n# SECURITY WARNING: don't run with debug turned on in production!\nDEBUG = True\nALLOWED_HOSTS = ['127.0.0.1']\n# Application definition\nINSTALLED_APPS = [",
        "detail": "djangochannelsapp.settings",
        "documentation": {}
    },
    {
        "label": "SECRET_KEY",
        "kind": 5,
        "importPath": "djangochannelsapp.settings",
        "description": "djangochannelsapp.settings",
        "peekOfCode": "SECRET_KEY = 'django-insecure-cz9wb(svs7nzs3w(%b(l!7hc&ux)#84!g-rim5uthh^e^m1v#v'\n# SECURITY WARNING: don't run with debug turned on in production!\nDEBUG = True\nALLOWED_HOSTS = ['127.0.0.1']\n# Application definition\nINSTALLED_APPS = [\n    #asgi integration\n    \"daphne\",\n    #asgi integration\n    'django.contrib.admin',",
        "detail": "djangochannelsapp.settings",
        "documentation": {}
    },
    {
        "label": "DEBUG",
        "kind": 5,
        "importPath": "djangochannelsapp.settings",
        "description": "djangochannelsapp.settings",
        "peekOfCode": "DEBUG = True\nALLOWED_HOSTS = ['127.0.0.1']\n# Application definition\nINSTALLED_APPS = [\n    #asgi integration\n    \"daphne\",\n    #asgi integration\n    'django.contrib.admin',\n    'django.contrib.auth',\n    'django.contrib.contenttypes',",
        "detail": "djangochannelsapp.settings",
        "documentation": {}
    },
    {
        "label": "ALLOWED_HOSTS",
        "kind": 5,
        "importPath": "djangochannelsapp.settings",
        "description": "djangochannelsapp.settings",
        "peekOfCode": "ALLOWED_HOSTS = ['127.0.0.1']\n# Application definition\nINSTALLED_APPS = [\n    #asgi integration\n    \"daphne\",\n    #asgi integration\n    'django.contrib.admin',\n    'django.contrib.auth',\n    'django.contrib.contenttypes',\n    'django.contrib.sessions',",
        "detail": "djangochannelsapp.settings",
        "documentation": {}
    },
    {
        "label": "INSTALLED_APPS",
        "kind": 5,
        "importPath": "djangochannelsapp.settings",
        "description": "djangochannelsapp.settings",
        "peekOfCode": "INSTALLED_APPS = [\n    #asgi integration\n    \"daphne\",\n    #asgi integration\n    'django.contrib.admin',\n    'django.contrib.auth',\n    'django.contrib.contenttypes',\n    'django.contrib.sessions',\n    'django.contrib.messages',\n    'django.contrib.staticfiles',",
        "detail": "djangochannelsapp.settings",
        "documentation": {}
    },
    {
        "label": "MIDDLEWARE",
        "kind": 5,
        "importPath": "djangochannelsapp.settings",
        "description": "djangochannelsapp.settings",
        "peekOfCode": "MIDDLEWARE = [\n    'django.middleware.security.SecurityMiddleware',\n    'django.contrib.sessions.middleware.SessionMiddleware',\n    'django.middleware.common.CommonMiddleware',\n    'django.middleware.csrf.CsrfViewMiddleware',\n    'django.contrib.auth.middleware.AuthenticationMiddleware',\n    'django.contrib.messages.middleware.MessageMiddleware',\n    'django.middleware.clickjacking.XFrameOptionsMiddleware',\n]\nROOT_URLCONF = 'djangochannelsapp.urls'",
        "detail": "djangochannelsapp.settings",
        "documentation": {}
    },
    {
        "label": "ROOT_URLCONF",
        "kind": 5,
        "importPath": "djangochannelsapp.settings",
        "description": "djangochannelsapp.settings",
        "peekOfCode": "ROOT_URLCONF = 'djangochannelsapp.urls'\nTEMPLATES = [\n    {\n        'BACKEND': 'django.template.backends.django.DjangoTemplates',\n        'DIRS': [],\n        'APP_DIRS': True,\n        'OPTIONS': {\n            'context_processors': [\n                'django.template.context_processors.debug',\n                'django.template.context_processors.request',",
        "detail": "djangochannelsapp.settings",
        "documentation": {}
    },
    {
        "label": "TEMPLATES",
        "kind": 5,
        "importPath": "djangochannelsapp.settings",
        "description": "djangochannelsapp.settings",
        "peekOfCode": "TEMPLATES = [\n    {\n        'BACKEND': 'django.template.backends.django.DjangoTemplates',\n        'DIRS': [],\n        'APP_DIRS': True,\n        'OPTIONS': {\n            'context_processors': [\n                'django.template.context_processors.debug',\n                'django.template.context_processors.request',\n                'django.contrib.auth.context_processors.auth',",
        "detail": "djangochannelsapp.settings",
        "documentation": {}
    },
    {
        "label": "ASGI_APPLICATION",
        "kind": 5,
        "importPath": "djangochannelsapp.settings",
        "description": "djangochannelsapp.settings",
        "peekOfCode": "ASGI_APPLICATION = 'djangochannelsapp.asgi.application'\n# Database\n# https://docs.djangoproject.com/en/4.2/ref/settings/#databases\nDATABASES = {\n    'default': {\n        'ENGINE': 'django.db.backends.mysql',\n        'NAME': 'customer_support',\n        'HOST':'localhost',\n        'USER':'root',\n        'PORT':'3306',",
        "detail": "djangochannelsapp.settings",
        "documentation": {}
    },
    {
        "label": "DATABASES",
        "kind": 5,
        "importPath": "djangochannelsapp.settings",
        "description": "djangochannelsapp.settings",
        "peekOfCode": "DATABASES = {\n    'default': {\n        'ENGINE': 'django.db.backends.mysql',\n        'NAME': 'customer_support',\n        'HOST':'localhost',\n        'USER':'root',\n        'PORT':'3306',\n        'PASSWORD':os.getenv('DB_PASSWORD')\n    }\n}",
        "detail": "djangochannelsapp.settings",
        "documentation": {}
    },
    {
        "label": "REST_FRAMEWORK",
        "kind": 5,
        "importPath": "djangochannelsapp.settings",
        "description": "djangochannelsapp.settings",
        "peekOfCode": "REST_FRAMEWORK = {\n    'DEFAULT_AUTHENTICATION_CLASSES': (\n        'rest_framework_simplejwt.authentication.JWTAuthentication',\n    ),\n    'DEFAULT_FILTER_BACKENDS': ['django_filters.rest_framework.DjangoFilterBackend'],\n    'COERCE_DECIMAL_TO_STRING' : False,\n}\nSIMPLE_JWT = {\n   'AUTH_HEADER_TYPES': ('JWT',),\n   \"ACCESS_TOKEN_LIFETIME\": timedelta(days=1),",
        "detail": "djangochannelsapp.settings",
        "documentation": {}
    },
    {
        "label": "SIMPLE_JWT",
        "kind": 5,
        "importPath": "djangochannelsapp.settings",
        "description": "djangochannelsapp.settings",
        "peekOfCode": "SIMPLE_JWT = {\n   'AUTH_HEADER_TYPES': ('JWT',),\n   \"ACCESS_TOKEN_LIFETIME\": timedelta(days=1),\n}\nAUTH_USER_MODEL = 'core.User'\nDJOSER = {\n    'SERIALIZERS': {\n        'user_create': 'core.serializers.UserCreateSerializer',\n        'user': 'core.serializers.UserSerializer',\n    }",
        "detail": "djangochannelsapp.settings",
        "documentation": {}
    },
    {
        "label": "AUTH_USER_MODEL",
        "kind": 5,
        "importPath": "djangochannelsapp.settings",
        "description": "djangochannelsapp.settings",
        "peekOfCode": "AUTH_USER_MODEL = 'core.User'\nDJOSER = {\n    'SERIALIZERS': {\n        'user_create': 'core.serializers.UserCreateSerializer',\n        'user': 'core.serializers.UserSerializer',\n    }\n}\n# Password validation\n# https://docs.djangoproject.com/en/4.2/ref/settings/#auth-password-validators\nAUTH_PASSWORD_VALIDATORS = [",
        "detail": "djangochannelsapp.settings",
        "documentation": {}
    },
    {
        "label": "DJOSER",
        "kind": 5,
        "importPath": "djangochannelsapp.settings",
        "description": "djangochannelsapp.settings",
        "peekOfCode": "DJOSER = {\n    'SERIALIZERS': {\n        'user_create': 'core.serializers.UserCreateSerializer',\n        'user': 'core.serializers.UserSerializer',\n    }\n}\n# Password validation\n# https://docs.djangoproject.com/en/4.2/ref/settings/#auth-password-validators\nAUTH_PASSWORD_VALIDATORS = [\n    {",
        "detail": "djangochannelsapp.settings",
        "documentation": {}
    },
    {
        "label": "AUTH_PASSWORD_VALIDATORS",
        "kind": 5,
        "importPath": "djangochannelsapp.settings",
        "description": "djangochannelsapp.settings",
        "peekOfCode": "AUTH_PASSWORD_VALIDATORS = [\n    {\n        'NAME': 'django.contrib.auth.password_validation.UserAttributeSimilarityValidator',\n    },\n    {\n        'NAME': 'django.contrib.auth.password_validation.MinimumLengthValidator',\n    },\n    {\n        'NAME': 'django.contrib.auth.password_validation.CommonPasswordValidator',\n    },",
        "detail": "djangochannelsapp.settings",
        "documentation": {}
    },
    {
        "label": "LANGUAGE_CODE",
        "kind": 5,
        "importPath": "djangochannelsapp.settings",
        "description": "djangochannelsapp.settings",
        "peekOfCode": "LANGUAGE_CODE = 'en-us'\nTIME_ZONE = 'UTC'\nUSE_I18N = True\nUSE_TZ = True\n# Static files (CSS, JavaScript, Images)\n# https://docs.djangoproject.com/en/4.2/howto/static-files/\nSTATIC_URL = '/static/'\nSTATIC_ROOT = os.path.join(BASE_DIR,'static')\nMEDIA_URL = '/media/'\nMEDIA_ROOT = os.path.join(BASE_DIR,'media')",
        "detail": "djangochannelsapp.settings",
        "documentation": {}
    },
    {
        "label": "TIME_ZONE",
        "kind": 5,
        "importPath": "djangochannelsapp.settings",
        "description": "djangochannelsapp.settings",
        "peekOfCode": "TIME_ZONE = 'UTC'\nUSE_I18N = True\nUSE_TZ = True\n# Static files (CSS, JavaScript, Images)\n# https://docs.djangoproject.com/en/4.2/howto/static-files/\nSTATIC_URL = '/static/'\nSTATIC_ROOT = os.path.join(BASE_DIR,'static')\nMEDIA_URL = '/media/'\nMEDIA_ROOT = os.path.join(BASE_DIR,'media')\n# Default primary key field type",
        "detail": "djangochannelsapp.settings",
        "documentation": {}
    },
    {
        "label": "USE_I18N",
        "kind": 5,
        "importPath": "djangochannelsapp.settings",
        "description": "djangochannelsapp.settings",
        "peekOfCode": "USE_I18N = True\nUSE_TZ = True\n# Static files (CSS, JavaScript, Images)\n# https://docs.djangoproject.com/en/4.2/howto/static-files/\nSTATIC_URL = '/static/'\nSTATIC_ROOT = os.path.join(BASE_DIR,'static')\nMEDIA_URL = '/media/'\nMEDIA_ROOT = os.path.join(BASE_DIR,'media')\n# Default primary key field type\n# https://docs.djangoproject.com/en/4.2/ref/settings/#default-auto-field",
        "detail": "djangochannelsapp.settings",
        "documentation": {}
    },
    {
        "label": "USE_TZ",
        "kind": 5,
        "importPath": "djangochannelsapp.settings",
        "description": "djangochannelsapp.settings",
        "peekOfCode": "USE_TZ = True\n# Static files (CSS, JavaScript, Images)\n# https://docs.djangoproject.com/en/4.2/howto/static-files/\nSTATIC_URL = '/static/'\nSTATIC_ROOT = os.path.join(BASE_DIR,'static')\nMEDIA_URL = '/media/'\nMEDIA_ROOT = os.path.join(BASE_DIR,'media')\n# Default primary key field type\n# https://docs.djangoproject.com/en/4.2/ref/settings/#default-auto-field\nDEFAULT_AUTO_FIELD = 'django.db.models.BigAutoField'",
        "detail": "djangochannelsapp.settings",
        "documentation": {}
    },
    {
        "label": "STATIC_URL",
        "kind": 5,
        "importPath": "djangochannelsapp.settings",
        "description": "djangochannelsapp.settings",
        "peekOfCode": "STATIC_URL = '/static/'\nSTATIC_ROOT = os.path.join(BASE_DIR,'static')\nMEDIA_URL = '/media/'\nMEDIA_ROOT = os.path.join(BASE_DIR,'media')\n# Default primary key field type\n# https://docs.djangoproject.com/en/4.2/ref/settings/#default-auto-field\nDEFAULT_AUTO_FIELD = 'django.db.models.BigAutoField'",
        "detail": "djangochannelsapp.settings",
        "documentation": {}
    },
    {
        "label": "STATIC_ROOT",
        "kind": 5,
        "importPath": "djangochannelsapp.settings",
        "description": "djangochannelsapp.settings",
        "peekOfCode": "STATIC_ROOT = os.path.join(BASE_DIR,'static')\nMEDIA_URL = '/media/'\nMEDIA_ROOT = os.path.join(BASE_DIR,'media')\n# Default primary key field type\n# https://docs.djangoproject.com/en/4.2/ref/settings/#default-auto-field\nDEFAULT_AUTO_FIELD = 'django.db.models.BigAutoField'",
        "detail": "djangochannelsapp.settings",
        "documentation": {}
    },
    {
        "label": "MEDIA_URL",
        "kind": 5,
        "importPath": "djangochannelsapp.settings",
        "description": "djangochannelsapp.settings",
        "peekOfCode": "MEDIA_URL = '/media/'\nMEDIA_ROOT = os.path.join(BASE_DIR,'media')\n# Default primary key field type\n# https://docs.djangoproject.com/en/4.2/ref/settings/#default-auto-field\nDEFAULT_AUTO_FIELD = 'django.db.models.BigAutoField'",
        "detail": "djangochannelsapp.settings",
        "documentation": {}
    },
    {
        "label": "MEDIA_ROOT",
        "kind": 5,
        "importPath": "djangochannelsapp.settings",
        "description": "djangochannelsapp.settings",
        "peekOfCode": "MEDIA_ROOT = os.path.join(BASE_DIR,'media')\n# Default primary key field type\n# https://docs.djangoproject.com/en/4.2/ref/settings/#default-auto-field\nDEFAULT_AUTO_FIELD = 'django.db.models.BigAutoField'",
        "detail": "djangochannelsapp.settings",
        "documentation": {}
    },
    {
        "label": "DEFAULT_AUTO_FIELD",
        "kind": 5,
        "importPath": "djangochannelsapp.settings",
        "description": "djangochannelsapp.settings",
        "peekOfCode": "DEFAULT_AUTO_FIELD = 'django.db.models.BigAutoField'",
        "detail": "djangochannelsapp.settings",
        "documentation": {}
    },
    {
        "label": "urlpatterns",
        "kind": 5,
        "importPath": "djangochannelsapp.urls",
        "description": "djangochannelsapp.urls",
        "peekOfCode": "urlpatterns = [\n    path('admin/', admin.site.urls),\n    path('playground/', include('playgrounds.urls')),\n    path('auth/', include('djoser.urls')),\n    path('auth/', include('djoser.urls.jwt'))\n]",
        "detail": "djangochannelsapp.urls",
        "documentation": {}
    },
    {
        "label": "application",
        "kind": 5,
        "importPath": "djangochannelsapp.wsgi",
        "description": "djangochannelsapp.wsgi",
        "peekOfCode": "application = get_wsgi_application()",
        "detail": "djangochannelsapp.wsgi",
        "documentation": {}
    },
    {
        "label": "MyappConfig",
        "kind": 6,
        "importPath": "myapp.apps",
        "description": "myapp.apps",
        "peekOfCode": "class MyappConfig(AppConfig):\n    default_auto_field = 'django.db.models.BigAutoField'\n    name = 'myapp'",
        "detail": "myapp.apps",
        "documentation": {}
    },
    {
        "label": "PlaygroundsConfig",
        "kind": 6,
        "importPath": "playgrounds.apps",
        "description": "playgrounds.apps",
        "peekOfCode": "class PlaygroundsConfig(AppConfig):\n    default_auto_field = 'django.db.models.BigAutoField'\n    name = 'playgrounds'",
        "detail": "playgrounds.apps",
        "documentation": {}
    },
    {
        "label": "urlpatterns",
        "kind": 5,
        "importPath": "playgrounds.urls",
        "description": "playgrounds.urls",
        "peekOfCode": "urlpatterns = [\n    path('hello/', hello, name='hello'),\n]",
        "detail": "playgrounds.urls",
        "documentation": {}
    },
    {
        "label": "hello",
        "kind": 2,
        "importPath": "playgrounds.views",
        "description": "playgrounds.views",
        "peekOfCode": "def hello(request):\n    return HttpResponse(\"OK\")",
        "detail": "playgrounds.views",
        "documentation": {}
    },
    {
        "label": "main",
        "kind": 2,
        "importPath": "manage",
        "description": "manage",
        "peekOfCode": "def main():\n    \"\"\"Run administrative tasks.\"\"\"\n    os.environ.setdefault('DJANGO_SETTINGS_MODULE', 'djangochannelsapp.settings')\n    try:\n        from django.core.management import execute_from_command_line\n    except ImportError as exc:\n        raise ImportError(\n            \"Couldn't import Django. Are you sure it's installed and \"\n            \"available on your PYTHONPATH environment variable? Did you \"\n            \"forget to activate a virtual environment?\"",
        "detail": "manage",
        "documentation": {}
    }
]